covid/__init__.py
covid/core.py
covid_api-2.1.dist-info/LICENSE
covid_api-2.1.dist-info/METADATA
covid_api-2.1.dist-info/WHEEL
covid_api-2.1.dist-info/top_level.txt
covid_api-2.1.dist-info/RECORD
