Metadata-Version: 2.1
Name: covid-api
Version: 2.1
Summary: Get info about any country using https://disease.sh api
Home-page: https://github.com/v1s1t0r999/CovidTracker/tree/v2-uc
Author: v1s1t0r999
Author-email: aditya.funs.11@gmail.com
License: MIT
Platform: UNKNOWN
Classifier: License :: OSI Approved :: MIT License
Classifier: Programming Language :: Python :: 3
Classifier: Programming Language :: Python :: 3.7
Requires-Python: >=3.6
